ankaios_sdk/__init__.py
ankaios_sdk/ankaios.py
ankaios_sdk/exceptions.py
ankaios_sdk/utils.py
ankaios_sdk/_components/__init__.py
ankaios_sdk/_components/complete_state.py
ankaios_sdk/_components/control_interface.py
ankaios_sdk/_components/file.py
ankaios_sdk/_components/log_campaign.py
ankaios_sdk/_components/manifest.py
ankaios_sdk/_components/request.py
ankaios_sdk/_components/response.py
ankaios_sdk/_components/workload.py
ankaios_sdk/_components/workload_builder.py
ankaios_sdk/_components/workload_state.py
ankaios_sdk/_protos/__init__.py
ankaios_sdk/_protos/ank_base_pb2.py
ankaios_sdk/_protos/ank_base_pb2_grpc.py
ankaios_sdk/_protos/control_api_pb2.py
ankaios_sdk/_protos/control_api_pb2_grpc.py
ankaios_sdk-0.7.0.dist-info/licenses/LICENSE
tests/__init__.py
tests/test_ankaios.py
tests/test_complete_state.py
tests/test_control_interface.py
tests/test_log_queue.py
tests/test_manifest.py
tests/test_utils.py
tests/test_workload_builder.py
tests/request/__init__.py
tests/request/test_get_state_request.py
tests/request/test_logs.py
tests/request/test_request.py
tests/request/test_update_state_request.py
tests/response/__init__.py
tests/response/test_log_response.py
tests/response/test_response.py
tests/response/test_update_state_success.py
tests/workload/__init__.py
tests/workload/test_access_right_rule.py
tests/workload/test_file.py
tests/workload/test_workload.py
tests/workload_state/__init__.py
tests/workload_state/test_workload_execution_state.py
tests/workload_state/test_workload_instance_name.py
tests/workload_state/test_workload_state.py
tests/workload_state/test_workload_state_collection.py
tests/workload_state/test_workload_state_enum.py
tests/workload_state/test_workload_substate_enum.py
ankaios_sdk-0.7.0.dist-info/METADATA
ankaios_sdk-0.7.0.dist-info/WHEEL
ankaios_sdk-0.7.0.dist-info/top_level.txt
ankaios_sdk-0.7.0.dist-info/RECORD
