Metadata-Version: 2.4
Name: ankaios-sdk
Version: 0.7.0
Summary: Eclipse Ankaios Python SDK - provides a convenient Python interface for interacting with the Ankaios platform.
Home-page: https://eclipse-ankaios.github.io/ankaios/latest/
Author: Elektrobit Automotive GmbH and Ankaios contributors
License: Apache-2.0
Project-URL: Documentation, https://eclipse-ankaios.github.io/ank-sdk-python/
Project-URL: Source, https://github.com/eclipse-ankaios/ank-sdk-python
Project-URL: Bug Tracker, https://github.com/eclipse-ankaios/ank-sdk-python/issues
Classifier: License :: OSI Approved :: Apache Software License
Classifier: Operating System :: POSIX :: Linux
Classifier: Programming Language :: Python :: 3
Classifier: Programming Language :: Python :: 3.9
Classifier: Programming Language :: Python :: 3.10
Classifier: Programming Language :: Python :: 3.11
Classifier: Programming Language :: Python :: 3.12
Classifier: Programming Language :: Python :: 3.13
Requires-Python: >=3.9
License-File: LICENSE
Requires-Dist: protobuf==5.29.5
Requires-Dist: PyYAML
Provides-Extra: dev
Requires-Dist: pytest; extra == "dev"
Requires-Dist: pytest-cov; extra == "dev"
Requires-Dist: pylint; extra == "dev"
Requires-Dist: pycodestyle; extra == "dev"
Provides-Extra: docs
Requires-Dist: sphinx; extra == "docs"
Requires-Dist: sphinx-rtd-theme; extra == "docs"
Requires-Dist: sphinx-autodoc-typehints; extra == "docs"
Requires-Dist: sphinx-mdinclude; extra == "docs"
Requires-Dist: sphinx-versioned-docs; extra == "docs"
Requires-Dist: google-api-python-client; extra == "docs"
Dynamic: classifier
Dynamic: description
Dynamic: description-content-type
Dynamic: home-page
Dynamic: license-file
Dynamic: project-url
Dynamic: provides-extra
Dynamic: requires-dist
Dynamic: requires-python
Dynamic: summary
